secret/SCRATCH.py
secret/__init__.py
tests/__init__.py
theming/__init__.py
theming/__main__.py
theming/version.py
theming-0.0.1.dist-info/LICENSE
theming-0.0.1.dist-info/METADATA
theming-0.0.1.dist-info/WHEEL
theming-0.0.1.dist-info/entry_points.txt
theming-0.0.1.dist-info/top_level.txt
theming-0.0.1.dist-info/RECORD
