Metadata-Version: 2.1
Name: theming
Version: 0.0.1
Summary: To Connect Apps With Users
Home-page: https://github.com/pyrustic/theming
Author: Pyrustic Evangelist
Author-email: pyrustic@protonmail.com
Maintainer: Pyrustic Evangelist
Maintainer-email: pyrustic@protonmail.com
License: MIT
Keywords: application-store,software-management,software-distribution,desktop-application,wheel-compatible
Platform: UNKNOWN
Classifier: Programming Language :: Python :: 3
Classifier: License :: OSI Approved :: MIT License
Classifier: Operating System :: OS Independent
Requires-Python: >=3.5
Requires-Dist: pyrustic
